rappilogs/__init__.py
rappilogs/main.py
rappilogs-1.0.0.data/scripts/main.py
rappilogs-1.0.0.dist-info/METADATA
rappilogs-1.0.0.dist-info/WHEEL
rappilogs-1.0.0.dist-info/top_level.txt
rappilogs-1.0.0.dist-info/RECORD
